wcosmo/__init__.py
wcosmo/_version.py
wcosmo/analytic.py
wcosmo/astropy.py
wcosmo/constants.py
wcosmo/integrate.py
wcosmo/taylor.py
wcosmo/utils.py
wcosmo/wcosmo.py
wcosmo/backend/__init__.py
wcosmo/backend/cupy.py
wcosmo/backend/jax.py
wcosmo/test/__init__.py
wcosmo/test/conftest.py
wcosmo/test/test_astropy.py
wcosmo/test/test_constants.py
wcosmo/test/test_cosmo.py
wcosmo/test/test_utils.py
wcosmo-0.5.4.dist-info/licenses/LICENSE
wcosmo-0.5.4.dist-info/METADATA
wcosmo-0.5.4.dist-info/WHEEL
wcosmo-0.5.4.dist-info/top_level.txt
wcosmo-0.5.4.dist-info/RECORD
