Metadata-Version: 2.4
Name: wcosmo
Version: 0.5.4
Summary: A package for cosmology calculations with arbitrary numpy-like APIs
Author: Amanda Farah
Author-email: Colm Talbot <talbotcolm@gmail.com>
License: MIT
Classifier: Framework :: Django
Classifier: Programming Language :: Python :: 3
Requires-Python: >=3.10
License-File: LICENSE
Requires-Dist: numpy
Requires-Dist: scipy
Requires-Dist: astropy>=6.1
Requires-Dist: plum-dispatch
Requires-Dist: array-api-compat
Provides-Extra: test
Requires-Dist: pytest-cov; extra == "test"
Requires-Dist: jax<0.7,>=0.4.34; python_version >= "3.11" and extra == "test"
Requires-Dist: jax<0.6,>=0.4.34; python_version < "3.11" and extra == "test"
Requires-Dist: unxt; extra == "test"
Provides-Extra: jax
Requires-Dist: jax>=0.4.34; python_version >= "3.11" and extra == "jax"
Requires-Dist: jax<0.6,>=0.4.34; python_version < "3.11" and extra == "jax"
Requires-Dist: unxt; extra == "jax"
Dynamic: license-file
